eventlog/__init__.py
eventlog/admin.py
eventlog/apps.py
eventlog/models.py
eventlog/services.py
eventlog/tests.py
eventlog/views.py
eventlog/locale/ru/LC_MESSAGES/django.mo
eventlog/locale/ru/LC_MESSAGES/django.po
eventlog/management/__init__.py
eventlog/management/commands/__init__.py
eventlog/management/commands/pruneeventlog.py
eventlog/migrations/0001_initial.py
eventlog/migrations/__init__.py
django_logging_eventlog-0.0.4.dist-info/LICENSE
django_logging_eventlog-0.0.4.dist-info/METADATA
django_logging_eventlog-0.0.4.dist-info/WHEEL
django_logging_eventlog-0.0.4.dist-info/top_level.txt
django_logging_eventlog-0.0.4.dist-info/RECORD
