Metadata-Version: 2.1
Name: django-logging-eventlog
Version: 0.0.4
Summary: Logger for the logging module that writes messages to the database
Home-page: https://github.com/mnemchinov/django-logging-eventlog
Author: mnemchinov
Author-email: mnemchinov@mail.ru
License: MIT License
Platform: UNKNOWN
Classifier: Development Status :: 4 - Beta
Classifier: Intended Audience :: Developers
Classifier: License :: OSI Approved :: MIT License
Classifier: Framework :: Django
Classifier: Environment :: Web Environment
Classifier: Natural Language :: Russian
Classifier: Natural Language :: English
Classifier: Operating System :: OS Independent
Classifier: Programming Language :: Python
Classifier: Topic :: Software Development
License-File: LICENSE
Requires-Dist: django (>=3.0)
